{"_id":"61c03a1ca4649d0beb2731de","title":"In darkness we plod toward","slug":"in-darkness-we-plod-toward","imageLink":"https://hunter-poem-images.s3.us-west-1.amazonaws.com/jan3_21.jpg","content":"In darkness we plod toward\nDays lending golden light within and without\nSmell of pine jars my senses and I wonder\nHow love reaches us so tender and miraculous\nAs if spirit abides, finding us at last.","isDraft":false,"hasTitle":true,"createdAt":"2021-12-20T08:09:00.608Z","updatedAt":"2021-12-20T08:09:00.608Z","__v":0}